revalsdk/__init__.py
revalsdk/authentication_pb2.py
revalsdk/authentication_pb2_grpc.py
revalsdk/functions.py
revalsdk/internal_pb2.py
revalsdk/internal_pb2_grpc.py
revalsdk/notification_pb2.py
revalsdk/notification_pb2_grpc.py
behtarino-0.0.9.dist-info/METADATA
behtarino-0.0.9.dist-info/WHEEL
behtarino-0.0.9.dist-info/top_level.txt
behtarino-0.0.9.dist-info/RECORD
